pyelexon/__init__.py
pyelexon/configure_logging.py
pyelexon/exceptions.py
pyelexon/kwargs_mapping.py
pyelexon/pyelexon.py
pyelexon-0.2.7.dist-info/WHEEL
pyelexon-0.2.7.dist-info/LICENSE.txt
pyelexon-0.2.7.dist-info/METADATA
pyelexon-0.2.7.dist-info/RECORD
